[
  {"model": "exchange.currency", "pk": "AED", "fields": {"name": "UAE Dirham"}},
  {"model": "exchange.currency", "pk": "AFN", "fields": {"name": "Afghan Afghani"}},
  {"model": "exchange.currency", "pk": "ALL", "fields": {"name": "Albanian Lek"}},
  {"model": "exchange.currency", "pk": "AMD", "fields": {"name": "Armenian Dram"}},
  {"model": "exchange.currency", "pk": "ANG", "fields": {"name": "Netherlands Antillian Guilder"}},
  {"model": "exchange.currency", "pk": "AOA", "fields": {"name": "Angolan Kwanza"}},
  {"model": "exchange.currency", "pk": "ARS", "fields": {"name": "Argentine Peso"}},
  {"model": "exchange.currency", "pk": "AUD", "fields": {"name": "Australian Dollar"}},
  {"model": "exchange.currency", "pk": "AWG", "fields": {"name": "Aruban Florin"}},
  {"model": "exchange.currency", "pk": "AZN", "fields": {"name": "Azerbaijani Manat"}},
  {"model": "exchange.currency", "pk": "BAM", "fields": {"name": "Bosnia and Herzegovina Convertible Mark"}},
  {"model": "exchange.currency", "pk": "BBD", "fields": {"name": "Barbadian Dollar"}},
  {"model": "exchange.currency", "pk": "BDT", "fields": {"name": "Bangladeshi Taka"}},
  {"model": "exchange.currency", "pk": "BGN", "fields": {"name": "Bulgarian Lev"}},
  {"model": "exchange.currency", "pk": "BHD", "fields": {"name": "Bahraini Dinar"}},
  {"model": "exchange.currency", "pk": "BMD", "fields": {"name": "Bermudian Dollar"}},
  {"model": "exchange.currency", "pk": "BND", "fields": {"name": "Brunei Dollar"}},
  {"model": "exchange.currency", "pk": "BOB", "fields": {"name": "Bolivian Boliviano"}},
  {"model": "exchange.currency", "pk": "BRL", "fields": {"name": "Brazilian Real"}},
  {"model": "exchange.currency", "pk": "BSD", "fields": {"name": "Bahamian Dollar"}},
  {"model": "exchange.currency", "pk": "BTN", "fields": {"name": "Bhutanese Ngultrum"}},
  {"model": "exchange.currency", "pk": "BWP", "fields": {"name": "Botswana Pula"}},
  {"model": "exchange.currency", "pk": "BYN", "fields": {"name": "Belarusian Ruble"}},
  {"model": "exchange.currency", "pk": "BZD", "fields": {"name": "Belize Dollar"}},
  {"model": "exchange.currency", "pk": "CAD", "fields": {"name": "Canadian Dollar"}},
  {"model": "exchange.currency", "pk": "CDF", "fields": {"name": "Congolese Franc"}},
  {"model": "exchange.currency", "pk": "CHF", "fields": {"name": "Swiss Franc"}},
  {"model": "exchange.currency", "pk": "CLP", "fields": {"name": "Chilean Peso"}},
  {"model": "exchange.currency", "pk": "CNY", "fields": {"name": "Chinese Renminbi"}},
  {"model": "exchange.currency", "pk": "COP", "fields": {"name": "Colombian Peso"}},
  {"model": "exchange.currency", "pk": "CRC", "fields": {"name": "Costa Rican Colon"}},
  {"model": "exchange.currency", "pk": "CUP", "fields": {"name": "Cuban Peso"}},
  {"model": "exchange.currency", "pk": "CVE", "fields": {"name": "Cape Verdean Escudo"}},
  {"model": "exchange.currency", "pk": "CZK", "fields": {"name": "Czech Koruna"}},
  {"model": "exchange.currency", "pk": "DJF", "fields": {"name": "Djiboutian Franc"}},
  {"model": "exchange.currency", "pk": "DKK", "fields": {"name": "Danish Krone"}},
  {"model": "exchange.currency", "pk": "DOP", "fields": {"name": "Dominican Peso"}},
  {"model": "exchange.currency", "pk": "DZD", "fields": {"name": "Algerian Dinar"}},
  {"model": "exchange.currency", "pk": "EGP", "fields": {"name": "Egyptian Pound"}},
  {"model": "exchange.currency", "pk": "ERN", "fields": {"name": "Eritrean Nakfa"}},
  {"model": "exchange.currency", "pk": "ETB", "fields": {"name": "Ethiopian Birr"}},
  {"model": "exchange.currency", "pk": "EUR", "fields": {"name": "Euro"}},
  {"model": "exchange.currency", "pk": "FJD", "fields": {"name": "Fijian Dollar"}},
  {"model": "exchange.currency", "pk": "FKP", "fields": {"name": "Falkland Islands Pound"}},
  {"model": "exchange.currency", "pk": "FOK", "fields": {"name": "Faroese Krona"}},
  {"model": "exchange.currency", "pk": "GBP", "fields": {"name": "British Pound Sterling"}},
  {"model": "exchange.currency", "pk": "GEL", "fields": {"name": "Georgian Lari"}},
  {"model": "exchange.currency", "pk": "GGP", "fields": {"name": "Guernsey Pound"}},
  {"model": "exchange.currency", "pk": "GHS", "fields": {"name": "Ghanaian Cedi"}},
  {"model": "exchange.currency", "pk": "GIP", "fields": {"name": "Gibraltar Pound"}},
  {"model": "exchange.currency", "pk": "GMD", "fields": {"name": "Gambian Dalasi"}},
  {"model": "exchange.currency", "pk": "GNF", "fields": {"name": "Guinean Franc"}},
  {"model": "exchange.currency", "pk": "GTQ", "fields": {"name": "Guatemalan Quetzal"}},
  {"model": "exchange.currency", "pk": "GYD", "fields": {"name": "Guyanese Dollar"}},
  {"model": "exchange.currency", "pk": "HKD", "fields": {"name": "Hong Kong Dollar"}},
  {"model": "exchange.currency", "pk": "HNL", "fields": {"name": "Honduran Lempira"}},
  {"model": "exchange.currency", "pk": "HRK", "fields": {"name": "Croatian Kuna"}},
  {"model": "exchange.currency", "pk": "HTG", "fields": {"name": "Haitian Gourde"}},
  {"model": "exchange.currency", "pk": "HUF", "fields": {"name": "Hungarian Forint"}},
  {"model": "exchange.currency", "pk": "IDR", "fields": {"name": "Indonesian Rupiah"}},
  {"model": "exchange.currency", "pk": "ILS", "fields": {"name": "Israeli New Shekel"}},
  {"model": "exchange.currency", "pk": "IMP", "fields": {"name": "Isle of Man Pound"}},
  {"model": "exchange.currency", "pk": "INR", "fields": {"name": "Indian Rupee"}},
  {"model": "exchange.currency", "pk": "IQD", "fields": {"name": "Iraqi Dinar"}},
  {"model": "exchange.currency", "pk": "IRR", "fields": {"name": "Iranian Rial"}},
  {"model": "exchange.currency", "pk": "ISK", "fields": {"name": "Icelandic Krona"}},
  {"model": "exchange.currency", "pk": "JEP", "fields": {"name": "Jersey Pound"}},
  {"model": "exchange.currency", "pk": "JMD", "fields": {"name": "Jamaican Dollar"}},
  {"model": "exchange.currency", "pk": "JOD", "fields": {"name": "Jordanian Dinar"}},
  {"model": "exchange.currency", "pk": "JPY", "fields": {"name": "Japanese Yen"}},
  {"model": "exchange.currency", "pk": "KES", "fields": {"name": "Kenyan Shilling"}},
  {"model": "exchange.currency", "pk": "KGS", "fields": {"name": "Kyrgyzstani Som"}},
  {"model": "exchange.currency", "pk": "KHR", "fields": {"name": "Cambodian Riel"}},
  {"model": "exchange.currency", "pk": "KID", "fields": {"name": "Kiribati Dollar"}},
  {"model": "exchange.currency", "pk": "KMF", "fields": {"name": "Comorian Franc"}},
  {"model": "exchange.currency", "pk": "KRW", "fields": {"name": "South Korean Won"}},
  {"model": "exchange.currency", "pk": "KWD", "fields": {"name": "Kuwaiti Dinar"}},
  {"model": "exchange.currency", "pk": "KYD", "fields": {"name": "Cayman Islands Dollar"}},
  {"model": "exchange.currency", "pk": "KZT", "fields": {"name": "Kazakhstani Tenge"}},
  {"model": "exchange.currency", "pk": "LAK", "fields": {"name": "Lao Kip"}},
  {"model": "exchange.currency", "pk": "LBP", "fields": {"name": "Lebanese Pound"}},
  {"model": "exchange.currency", "pk": "LKR", "fields": {"name": "Sri Lanka Rupee"}},
  {"model": "exchange.currency", "pk": "LRD", "fields": {"name": "Liberian Dollar"}},
  {"model": "exchange.currency", "pk": "LSL", "fields": {"name": "Lesotho Loti"}},
  {"model": "exchange.currency", "pk": "LYD", "fields": {"name": "Libyan Dinar"}},
  {"model": "exchange.currency", "pk": "MAD", "fields": {"name": "Moroccan Dirham"}},
  {"model": "exchange.currency", "pk": "MDL", "fields": {"name": "Moldovan Leu"}},
  {"model": "exchange.currency", "pk": "MGA", "fields": {"name": "Malagasy Ariary"}},
  {"model": "exchange.currency", "pk": "MKD", "fields": {"name": "Macedonian Denar"}},
  {"model": "exchange.currency", "pk": "MMK", "fields": {"name": "Burmese Kyat"}},
  {"model": "exchange.currency", "pk": "MNT", "fields": {"name": "Mongolian Togrog"}},
  {"model": "exchange.currency", "pk": "MOP", "fields": {"name": "Macanese Pataca"}},
  {"model": "exchange.currency", "pk": "MRU", "fields": {"name": "Mauritanian Ouguiya"}},
  {"model": "exchange.currency", "pk": "MUR", "fields": {"name": "Mauritian Rupee"}},
  {"model": "exchange.currency", "pk": "MVR", "fields": {"name": "Maldivian Rufiyaa"}},
  {"model": "exchange.currency", "pk": "MWK", "fields": {"name": "Malawian Kwacha"}},
  {"model": "exchange.currency", "pk": "MXN", "fields": {"name": "Mexican Peso"}},
  {"model": "exchange.currency", "pk": "MYR", "fields": {"name": "Malaysian Ringgit"}},
  {"model": "exchange.currency", "pk": "MZN", "fields": {"name": "Mozambican Metical"}},
  {"model": "exchange.currency", "pk": "NAD", "fields": {"name": "Namibian Dollar"}},
  {"model": "exchange.currency", "pk": "NGN", "fields": {"name": "Nigerian Naira"}},
  {"model": "exchange.currency", "pk": "NIO", "fields": {"name": "Nicaraguan Cordoba"}},
  {"model": "exchange.currency", "pk": "NOK", "fields": {"name": "Norwegian Krone"}},
  {"model": "exchange.currency", "pk": "NPR", "fields": {"name": "Nepali Rupee"}},
  {"model": "exchange.currency", "pk": "NZD", "fields": {"name": "New Zealand Dollar"}},
  {"model": "exchange.currency", "pk": "OMR", "fields": {"name": "Omani Rial"}},
  {"model": "exchange.currency", "pk": "PAB", "fields": {"name": "Panamanian Balboa"}},
  {"model": "exchange.currency", "pk": "PEN", "fields": {"name": "Peruvian Sol"}},
  {"model": "exchange.currency", "pk": "PGK", "fields": {"name": "Papua New Guinean Kina"}},
  {"model": "exchange.currency", "pk": "PHP", "fields": {"name": "Philippine Peso"}},
  {"model": "exchange.currency", "pk": "PKR", "fields": {"name": "Pakistani Rupee"}},
  {"model": "exchange.currency", "pk": "PLN", "fields": {"name": "Polish Zloty"}},
  {"model": "exchange.currency", "pk": "PYG", "fields": {"name": "Paraguayan Guarani"}},
  {"model": "exchange.currency", "pk": "QAR", "fields": {"name": "Qatari Riyal"}},
  {"model": "exchange.currency", "pk": "RON", "fields": {"name": "Romanian Leu"}},
  {"model": "exchange.currency", "pk": "RSD", "fields": {"name": "Serbian Dinar"}},
  {"model": "exchange.currency", "pk": "RUB", "fields": {"name": "Russian Ruble"}},
  {"model": "exchange.currency", "pk": "RWF", "fields": {"name": "Rwandan Franc"}},
  {"model": "exchange.currency", "pk": "SAR", "fields": {"name": "Saudi Riyal"}},
  {"model": "exchange.currency", "pk": "SBD", "fields": {"name": "Solomon Islands Dollar"}},
  {"model": "exchange.currency", "pk": "SCR", "fields": {"name": "Seychellois Rupee"}},
  {"model": "exchange.currency", "pk": "SDG", "fields": {"name": "Sudanese Pound"}},
  {"model": "exchange.currency", "pk": "SEK", "fields": {"name": "Swedish Krona"}},
  {"model": "exchange.currency", "pk": "SGD", "fields": {"name": "Singapore Dollar"}},
  {"model": "exchange.currency", "pk": "SHP", "fields": {"name": "Saint Helena Pound"}},
  {"model": "exchange.currency", "pk": "SLE", "fields": {"name": "Sierra Leonean Leone"}},
  {"model": "exchange.currency", "pk": "SLL", "fields": {"name": "Sierra Leonean Leone (old)"}},
  {"model": "exchange.currency", "pk": "SOS", "fields": {"name": "Somali Shilling"}},
  {"model": "exchange.currency", "pk": "SRD", "fields": {"name": "Surinamese Dollar"}},
  {"model": "exchange.currency", "pk": "SSP", "fields": {"name": "South Sudanese Pound"}},
  {"model": "exchange.currency", "pk": "STN", "fields": {"name": "Sao Tome and Principe Dobra"}},
  {"model": "exchange.currency", "pk": "SYP", "fields": {"name": "Syrian Pound"}},
  {"model": "exchange.currency", "pk": "SZL", "fields": {"name": "Swazi Lilangeni"}},
  {"model": "exchange.currency", "pk": "THB", "fields": {"name": "Thai Baht"}},
  {"model": "exchange.currency", "pk": "TJS", "fields": {"name": "Tajikistani Somoni"}},
  {"model": "exchange.currency", "pk": "TMT", "fields": {"name": "Turkmenistan Manat"}},
  {"model": "exchange.currency", "pk": "TND", "fields": {"name": "Tunisian Dinar"}},
  {"model": "exchange.currency", "pk": "TOP", "fields": {"name": "Tongan Paanga"}},
  {"model": "exchange.currency", "pk": "TRY", "fields": {"name": "Turkish Lira"}},
  {"model": "exchange.currency", "pk": "TTD", "fields": {"name": "Trinidad and Tobago Dollar"}},
  {"model": "exchange.currency", "pk": "TVD", "fields": {"name": "Tuvaluan Dollar"}},
  {"model": "exchange.currency", "pk": "TWD", "fields": {"name": "New Taiwan Dollar"}},
  {"model": "exchange.currency", "pk": "TZS", "fields": {"name": "Tanzanian Shilling"}},
  {"model": "exchange.currency", "pk": "UAH", "fields": {"name": "Ukrainian Hryvnia"}},
  {"model": "exchange.currency", "pk": "UGX", "fields": {"name": "Ugandan Shilling"}},
  {"model": "exchange.currency", "pk": "USD", "fields": {"name": "US Dollar"}},
  {"model": "exchange.currency", "pk": "UYU", "fields": {"name": "Uruguayan Peso"}},
  {"model": "exchange.currency", "pk": "UZS", "fields": {"name": "Uzbekistani Som"}},
  {"model": "exchange.currency", "pk": "VES", "fields": {"name": "Venezuelan Bolivar Soberano"}},
  {"model": "exchange.currency", "pk": "VND", "fields": {"name": "Vietnamese Dong"}},
  {"model": "exchange.currency", "pk": "VUV", "fields": {"name": "Vanuatu Vatu"}},
  {"model": "exchange.currency", "pk": "WST", "fields": {"name": "Samoan Tala"}},
  {"model": "exchange.currency", "pk": "XAF", "fields": {"name": "Central African CFA Franc"}},
  {"model": "exchange.currency", "pk": "XCD", "fields": {"name": "East Caribbean Dollar"}},
  {"model": "exchange.currency", "pk": "XDR", "fields": {"name": "Special Drawing Rights"}},
  {"model": "exchange.currency", "pk": "XOF", "fields": {"name": "West African CFA Franc"}},
  {"model": "exchange.currency", "pk": "XPF", "fields": {"name": "CFP Franc"}},
  {"model": "exchange.currency", "pk": "YER", "fields": {"name": "Yemeni Rial"}},
  {"model": "exchange.currency", "pk": "ZAR", "fields": {"name": "South African Rand"}},
  {"model": "exchange.currency", "pk": "ZMW", "fields": {"name": "Zambian Kwacha"}},
  {"model": "exchange.currency", "pk": "ZWL", "fields": {"name": "Zimbabwean Dollar"}}
]
